programl-0.3.2.data/purelib/programl/__init__.py
programl-0.3.2.data/purelib/programl/create_ops.py
programl-0.3.2.data/purelib/programl/exceptions.py
programl-0.3.2.data/purelib/programl/serialize_ops.py
programl-0.3.2.data/purelib/programl/transform_ops.py
programl-0.3.2.data/purelib/programl/version.py
programl-0.3.2.data/purelib/programl/bin/clang2graph-10
programl-0.3.2.data/purelib/programl/bin/graph2dot
programl-0.3.2.data/purelib/programl/bin/graph2json
programl-0.3.2.data/purelib/programl/bin/llvm2graph-10
programl-0.3.2.data/purelib/programl/bin/llvm2graph-3.8
programl-0.3.2.data/purelib/programl/bin/llvm2graph-6
programl-0.3.2.data/purelib/programl/bin/xla2graph
programl-0.3.2.data/purelib/programl/ir/llvm/__init__.py
programl-0.3.2.data/purelib/programl/ir/llvm/inst2vec_encoder.py
programl-0.3.2.data/purelib/programl/ir/llvm/internal/inst2vec_augmented_dictionary.pickle
programl-0.3.2.data/purelib/programl/ir/llvm/internal/inst2vec_augmented_embeddings.pickle
programl-0.3.2.data/purelib/programl/proto/__init__.py
programl-0.3.2.data/purelib/programl/proto/program_graph_pb2.py
programl-0.3.2.data/purelib/programl/proto/util_pb2.py
programl-0.3.2.data/purelib/programl/third_party/inst2vec/__init__.py
programl-0.3.2.data/purelib/programl/third_party/inst2vec/inst2vec_preprocess.py
programl-0.3.2.data/purelib/programl/third_party/inst2vec/rgx_utils.py
programl-0.3.2.data/purelib/programl/third_party/tensorflow/__init__.py
programl-0.3.2.data/purelib/programl/third_party/tensorflow/features_pb2.py
programl-0.3.2.data/purelib/programl/third_party/tensorflow/xla_pb2.py
programl-0.3.2.data/purelib/programl/util/py/__init__.py
programl-0.3.2.data/purelib/programl/util/py/cc_system_includes.py
programl-0.3.2.data/purelib/programl/util/py/decorators.py
programl-0.3.2.data/purelib/programl/util/py/executor.py
programl-0.3.2.data/purelib/programl/util/py/humanize.py
programl-0.3.2.data/purelib/programl/util/py/init_app.py
programl-0.3.2.dist-info/LICENSE
programl-0.3.2.dist-info/METADATA
programl-0.3.2.dist-info/WHEEL
programl-0.3.2.dist-info/top_level.txt
programl-0.3.2.dist-info/RECORD
