Metadata-Version: 2.1
Name: programl
Version: 0.3.2
Summary: A Graph-based Program Representation for Data Flow Analysis and Compiler Optimizations
Home-page: https://github.com/ChrisCummins/ProGraML
Author: Chris Cummins
License: Apache 2.0
Platform: macosx-10.15-x86_64
Classifier: Development Status :: 3 - Alpha
Classifier: Environment :: Console
Classifier: Intended Audience :: Developers
Classifier: Intended Audience :: Science/Research
Classifier: License :: OSI Approved :: Apache Software License
Classifier: Programming Language :: Python :: 3.6
Classifier: Programming Language :: Python :: 3.7
Classifier: Programming Language :: Python :: 3.8
Classifier: Programming Language :: Python :: 3.9
Classifier: Programming Language :: Python :: 3
Classifier: Topic :: Scientific/Engineering :: Artificial Intelligence
Classifier: Topic :: Software Development :: Compilers
Requires-Python: >=3.6
License-File: LICENSE
Requires-Dist: absl-py (>=0.11.0)
Requires-Dist: dgl (>=0.6.1)
Requires-Dist: grpcio (>=1.33.2)
Requires-Dist: networkx (>=2.4)
Requires-Dist: numpy (>=1.19.3)
Requires-Dist: protobuf (>=3.13.0)
Requires-Dist: torch (>=1.8.0)
Requires-Dist: tqdm (>=4.38.0)
